pynlcd/__init__.py
pynlcd/nlcd.py
pynlcd-0.1.4.dist-info/LICENSE
pynlcd-0.1.4.dist-info/METADATA
pynlcd-0.1.4.dist-info/WHEEL
pynlcd-0.1.4.dist-info/entry_points.txt
pynlcd-0.1.4.dist-info/top_level.txt
pynlcd-0.1.4.dist-info/RECORD
