Metadata-Version: 2.1
Name: pynlcd
Version: 0.1.4
Summary: A Python package for downloading NLCD data
Author-email: Saswata Nandi <iamsaswata@yahoo.com>
Project-URL: Homepage, https://github.com/iamsaswata/pynlcd
Project-URL: Bug Tracker, https://github.com/iamsaswata/pynlcd/issues
Project-URL: Documentation, https://pynlcd.readthedocs.io
Classifier: Development Status :: 4 - Beta
Classifier: Programming Language :: Python :: 3
Classifier: License :: OSI Approved :: MIT License
Classifier: Operating System :: OS Independent
Classifier: Topic :: Scientific/Engineering :: Hydrology
Requires-Python: >=3.7
License-File: LICENSE
Requires-Dist: python-dateutil>=2.9.0
Requires-Dist: requests>=2.31.0
Requires-Dist: pyproj>=3.3
Requires-Dist: scipy>=1.13.0
Requires-Dist: GDAL>=3.7.0
